pyfhog/__init__.py
pyfhog/_pyfhog.cpython-38-aarch64-linux-gnu.so
pyfhog-0.1.4.dist-info/LICENSE
pyfhog-0.1.4.dist-info/METADATA
pyfhog-0.1.4.dist-info/WHEEL
pyfhog-0.1.4.dist-info/top_level.txt
pyfhog-0.1.4.dist-info/RECORD
