Metadata-Version: 2.4
Name: pyfhog
Version: 0.1.4
Summary: Fast FHOG feature extraction for Python
Home-page: https://github.com/johnwilsoniv/pyfhog
Author: SplitFace Project
Author-email: 
License: Boost Software License 1.0
Project-URL: Homepage, https://github.com/johnwilsoniv/pyfhog
Project-URL: Documentation, https://github.com/johnwilsoniv/pyfhog#readme
Project-URL: Repository, https://github.com/johnwilsoniv/pyfhog.git
Project-URL: Issues, https://github.com/johnwilsoniv/pyfhog/issues
Keywords: hog,fhog,feature-extraction,computer-vision,facial-analysis
Classifier: Development Status :: 3 - Alpha
Classifier: Intended Audience :: Developers
Classifier: Topic :: Scientific/Engineering :: Image Recognition
Classifier: Programming Language :: Python :: 3
Requires-Python: >=3.8
License-File: LICENSE
Requires-Dist: numpy>=1.20.0
Dynamic: home-page
Dynamic: license-file
Dynamic: requires-python
